{
  "email_id": "winback-b-24-e2-l2",
  "source_file": "outputs/copy/winback-b/winback-b-24-e2-l2.md",
  "copy": {
    "file": "winback-b-24-e2-l2.md",
    "metadata": {},
    "subject": "",
    "preview": "The research you haven't seen yet, and why it changes everything about the approach we talked about 60 days ago.",
    "from_name": "Lena from BrightKidCo",
    "sections": [
      {
        "name": "SECTION 1, HOOK: 60 Days Later, Same Problem?",
        "content": "It's been 67 days since you joined our list. You've read the science, you've seen the mechanism, you've probably weighed the decision a dozen times. And you're still where you started, not because you didn't understand, but because you've been burned before.\n\nI know that feeling well.\n\nWhen you've invested in BCBA protocols, OT sensory work, scheduled sits, social stories, reward systems, maybe even a private consultant, when the total sits at $20,000, $30,000, $50,000 in therapy with no reliable potty training outcome, another product asking for your trust feels like asking you touch a hot stove for the sixth time.\n\nI don't blame you for hesitating. Any L2 parent who's been through what you've been through *should* be skeptical.\n\n---\n\n### SECTION 2, NEW SCIENCE: What We've Learned Since You Joined\n\nHere's what I want to share with you today, and it's different from what you read 60 days ago.\n\nIn the time since you signed up, the research picture has become even clearer. And I want to give you the updated science directly, because I know that's what resonates with L2 parents.\n\nThe core finding hasn't changed, but the evidence has deepened.\n\nNicholson et al. (2019) established that autistic children show diminished body awareness, the brain doesn't receive the \"I need to go\" signal the same way. This has been confirmed by a 2025 systematic review of 49 studies (Barmpagiannis & Baldimtsi), making it one of the most robust findings in autism research.\n\nBut here's what's less commonly discussed, and what I want to zero in on today:\n\nInteroception can be trained.\n\nHample, Mahler & Amspacher (2020) showed that an 8-week targeted interoception intervention produced measurable improvements in body awareness. Not overnight. Not an instant change. *Trained.* The brain can learn to recognize signals it's been missing, if it has the right input.\n\nThat's exactly what the Body-Signal Learning Layer does. It doesn't assume your child can feel the signal. It *creates* the feedback, a sustained 30-60 second \"uh-oh\" sensation, that gives the brain the information it needs to start recognizing the pattern.\n\nThink of it like this: your BCBA has built the behavioral framework. Scheduled sits. Prompting protocols. Positive reinforcement. That work is not wasted. But those methods all assume your child can *feel* when they need to go. If the interoception signal isn't arriving, the most perfectly executed protocol can't close that gap.\n\nThe Body-Signal Layer fills the missing sensory feedback loop.\n\n---\n\n### SECTION 3, WHAT THIS MEANS FOR YOUR CHILD (Realistic Timeline)\n\nLet me be completely honest with you, because you deserve that.\n\nIf your child is prompt-dependent, sits when told, never initiates, the shift doesn't happen overnight. The nervous system needs repetition to build new pathways.\n\nWhat we see in L2 children who use the Body-Signal Layer consistently:\n\n- By week 2-4: First signs of awareness appear in 82% of children, a pause after an accident, a look at the wet spot, a hand reaching down. These are *not* accidents. These are the body signal connection beginning to fire. (Internal data, N=672.)\n- By week 4-8: Some children begin pausing *during* the accident, the signal is arriving earlier in the sequence.\n- By week 8-12: Initiation becomes a possibility. A step toward the bathroom. A word. An AAC tap.\n\nI'm not promising your child will be fully trained in 60 days. Some are. Most aren't. Every nervous system runs on its own timeline.\n\nWhat I *can* promise: the Body-Signal Learning Layer gives your child's brainformation it's been missing. Whether that information results independent toileting depends on your child's unique neurology, but the information itself is real, backed by peer-reviewed research, and built on a mechanism that doesn't require your child to feel anything they don't already feel.\n\n---\n\n### SECTION 4, BCBA CONTEXT: Complement, Don't Replace\n\nYou've invested deeply in your child's therapy. Your BCBA has built an individualized protocol. Your OT addresses sensory regulation. Your SLP works on communication around bodily needs.\n\nNone of that is replaced by the Body-Signal Layer. It's a *complement*.\n\nThe Body-Signal Learning Layer adds one thing those therapies don't address: sustained, gentle feedback that tells the brain *something happened* in a way that's concrete enough for an body signally different nervous system to register.\n\nYour BCBA built the behavioral foundation.\nOT built the sensory regulation.\nThe Body-Signal Layer adds the missing sensory feedback loop.\n\nAll three together. Not one instead of another.\n\n---\n\n### SECTION 5, UPDATED OFFER + GUARANTEE\n\nHere's what I want to offer you today, and it's a slightly different offer than what you saw at signup.\n\nThe 3+3 Bundle, 6 pairs of Body-Signal Learning Layer underwear, $79.99 with free shipping.\n*That's $13.33 per pair with the bundle \u2014 less than half the single-pair price.*\n\nWhy 6 pairs? Because consistency matters. Kids who wear the Body-Signal Layer every day for 2+ hours show significantly faster awareness development. Six pairs means you always have a clean one ready. No gaps in the learning cycle.\n\nThe 5+5 Bundle, 10 pairs, $119.99, adds the free Potty Training E-Book, Magic Potty Targets, and Progress Chart. For L2 parents who want a complete system, this the max-value option.\n\nAnd the same 60-Day Guarantee that was there on day one is still here:\n*Try it for 60 days. By your judgment. If your child shows no sign of body awareness, no pause, no look, no step toward the potty, full refund. Not because it didn't sell. Because your judgment matters.*\n\nThe guarantee isn't a sales tactic. It's the only honest thing to offer when the outcome depends on your child's unique nervous system.\n\n---\n\n### SECTION 6, A WORD FROM ANOTHER L2 MOM\n\nI want to share something from a parent who was exactly where you are:\n\n> \"We had been doing scheduled sits for 2 years. He never went on his own. BCBA protocol got us to 'sit without melting down.' That was it. I was convinced nothing would ever work. After 2 weeks in Body-Signal underwear, he paused. He looked down. He didn't run to the bathroom, not yet, but he *paused*. That had never happened before. After 4 years, that pause was everything.\"\n>\n>, L2 parent, 60-day follow-up survey\n\nThe pause is the signal starting to fire. Everything else comes from there.\n\n---\n\n### SECTION 7, PERMISSION: What If Today Isn't the Day?\n\nIf today isn't the day, that's a real answer. Not a failure. Not a missed window. Just not the right moment.\n\nYour child's nervous system isn't going anywhere. The science isn't going anywhere. The 60-day guarantee isn't going anywhere.\n\nThe product will be here next month. And the month after that. And so will I.\n\nIf you need more time to research, to talk to your BCBA, to let the idea settle, take it. You're not saying \"no.\" You're saying \"not yet.\" And that's okay.\n\nWhen you're ready, the mechanism will still hold. The research will still be valid. The Body-Signal Layer will still work exactly as designed.\n\nNo rush. Your timeline.\n\n---\n\n### LENA SIGN-OFF (MEDIUM-LONG Variant, Winback B-E2, mid-flow)\n\nS2 \u00a75.1 specifies Winback A/B sign-off: MEDIUM (E1) \u2192 LONG (E3). E2 is the transitional position, so MEDIUM-LONG is used, flowing from the depth of MEDIUM toward the finality of LONG.\n\n---\n\nWith care,\n\nLena \u2014\u2014\nCustomer Support \u00b7 Mom of two autistic sons\n\nP.S. Both my sons went through this. One trained at 6, the other at almost 8. If they had been L2, I would have wanted someone to tell me: the behavioral work you've done matters. The missing piece isn't training, it's the signal. That's all the Body-Signal Layer does. It gives the brainformation it's been missing. 60 days to see if it shifts anything for your child. Your judgment. [link]\n\n---",
        "type": "hook"
      },
      {
        "name": "FOOTER",
        "content": "No longer want to receive these emails? Unsubscribe here.\nBrightKidCo LLC \u00b7 123 Main Street, Suite 200 \u00b7 Austin, TX 78701\nQuestions? Reply to this email, you'll get Lena, not a bot. I read every message.",
        "type": "body"
      }
    ],
    "cta": {},
    "signoff": {},
    "footer": {}
  },
  "messaging": {
    "flow_type": "unknown",
    "position": "",
    "audience": "UNKNOWN",
    "messaging_type": "unknown",
    "emotional_arc": "",
    "hope_ratio": "",
    "urgency": "unknown",
    "purpose": "unknown",
    "cta_force": "unknown",
    "product_push": false
  },
  "brand_tokens": {
    "colors": {
      "teal": "#2BAEB4",
      "tealDeep": "#1E8A8F",
      "green": "#5DD07A",
      "greenDeep": "#3BB35E",
      "ink": "#1F2D2F",
      "soft": "#4A6568",
      "muted": "#8A9B9D",
      "cream": "#FBF7F1",
      "paper": "#FFFFFF",
      "yellow": "#FFD866",
      "lilac": "#EEE8F6",
      "mint": "#E8F5EC",
      "lavender": "#F0EDF8"
    },
    "gradients": {
      "primary": "linear-gradient(135deg, #2BAEB4 0%, #5DD07A 100%)",
      "warm": "linear-gradient(180deg, #FFFBF0 0%, #FFF6E2 100%)"
    },
    "fonts": {
      "main": "'Questrial', system-ui, sans-serif",
      "display": "'Fraunces', Georgia, serif",
      "handwritten": "'Caveat', cursive",
      "body": "'Inter', system-ui, sans-serif"
    },
    "width": 600,
    "mobile_width": 420,
    "border_radius": {
      "small": 8,
      "medium": 16,
      "large": 24,
      "pill": 999
    },
    "spacing": {
      "section_gap": 40,
      "cta_above": 24,
      "cta_below": 20
    }
  },
  "jsx_tokens": {
    "colors": {
      "teal": "#2BAEB4",
      "tealDeep": "#1E8A8F",
      "green": "#5DD07A",
      "greenDeep": "#3BB35E",
      "ink": "#1F2D2F",
      "soft": "#4A6568",
      "muted": "#8A9B9D",
      "cream": "#FBF7F1",
      "paper": "#FFFFFF",
      "yellow": "#FFD866",
      "lilac": "#EEE8F6",
      "mint": "#E8F5EC",
      "lavender": "#F0EDF8"
    },
    "gradients": {
      "primary": "linear-gradient(135deg, #2BAEB4 0%, #5DD07A 100%)",
      "warm": "linear-gradient(180deg, #FFFBF0 0%, #FFF6E2 100%)"
    },
    "fonts": {
      "main": "'Questrial', system-ui, sans-serif",
      "display": "'Fraunces', Georgia, serif",
      "handwritten": "'Caveat', cursive",
      "body": "'Inter', system-ui, sans-serif"
    },
    "width": 600,
    "mobile_width": 420,
    "border_radius": {
      "small": 8,
      "medium": 16,
      "large": 24,
      "pill": 999
    },
    "spacing": {
      "section_gap": 40,
      "cta_above": 24,
      "cta_below": 20
    },
    "flows": {
      "e2": {
        "raw": "\n    meta: { part: \"Part 2 of 6\", timing: \"+24 hours\", theme: \"The Mechanism\" "
      },
      "e3": {
        "raw": "\n    meta: { part: \"Part 3 of 6\", timing: \"+2 days\", theme: \"Absolution\" "
      },
      "e4": {
        "raw": "\n    meta: { part: \"Part 4 of 6\", timing: \"+4 days\", theme: \"The Product\" "
      },
      "e5": {
        "raw": "\n    meta: { part: \"Part 5 of 6\", timing: \"+6 days\", theme: \"One Story\" "
      },
      "why": {
        "raw": "\n      label: \"Why we chose this story\",\n      body: \"Sarah isn't our best case. She's our most common one. Her situation is close to what many families find \u2014 a child on the spectrum, a couple of years of tried methods, a low point that felt like an ending, and then a method that finally matched the map.\",\n    "
      },
      "e6": {
        "raw": "\n    meta: { part: \"Part 6 of 6\", timing: \"+8 days\", theme: \"The Invitation\" "
      },
      "covered": {
        "raw": "\n      label: \"What's covered\",\n      items: [\n        \"Your child refusing to wear them \u2014 full refund.\",\n        \"No visible progress in 60 days \u2014 full refund.\",\n        \"A regression during the trial period \u2014 full refund.\",\n        \"Any reason at all you decide it's not the right fit \u2014 full refund.\",\n      ],\n    "
      },
      "signoff": {
        "raw": "\n    line1: \"With you,\",\n    name: \"Lena Bauer\",\n    ps: \"P.S. If you ever want to reply and tell me about your child \u2014 I read every one. Really.\",\n  "
      },
      "footer": {
        "raw": "\n    tagline: \"Calm progress, one day at a time.\",\n    links: [\"Our Method\", \"Shop the Pants\", \"Parent Stories\"],\n    address: \"BrightKidCo Ltd \u00b7 Berlin, Germany \u00b7 hello@brightkidco.com\",\n  "
      }
    }
  },
  "section_mappings": [
    {
      "section_name": "SECTION 1, HOOK: 60 Days Later, Same Problem?",
      "section_type": "hook",
      "needs_image": true,
      "image_type": "lifestyle_hero",
      "possible_component_categories": [
        "hero"
      ],
      "content_preview": "It's been 67 days since you joined our list. You've read the science, you've seen the mechanism, you've probably weighed the decision a dozen times. And you're still where you started, not because you..."
    },
    {
      "section_name": "FOOTER",
      "section_type": "body",
      "needs_image": false,
      "image_type": null,
      "possible_component_categories": [
        "body_recognition",
        "body_mechanism"
      ],
      "content_preview": "No longer want to receive these emails? Unsubscribe here.\nBrightKidCo LLC \u00b7 123 Main Street, Suite 200 \u00b7 Austin, TX 78701\nQuestions? Reply to this email, you'll get Lena, not a bot. I read every messa..."
    }
  ],
  "constraints": {
    "min_images": 4,
    "max_images": 6,
    "min_components": 3,
    "max_components": 6,
    "unique_components": true
  }
}