{
  "email_id": "welcome-01-e8-l3",
  "section_0": {
    "section_type": "hero",
    "section_name": "HOOK",
    "component_id": "M1",
    "component_name": "Emotional Hero (Storytelling Open)",
    "component_source": "A",
    "image_file": "toddlers-backview-disposable-diapers.png",
    "image_category": "lifestyle"
  },
  "section_1": {
    "section_type": "product",
    "section_name": "Product Showcase",
    "component_id": "PRODEEP-8",
    "component_name": "The Bundle Builder",
    "component_source": "A*",
    "image_file": "training-pant-penguin-multicolor.jpg",
    "image_category": "flat-lay"
  },
  "section_2": {
    "section_type": "guarantee",
    "section_name": "Guarantee",
    "component_id": "TRUST-8",
    "component_name": "Trust Icons Row",
    "component_source": "A*",
    "image_file": "toddler-playing-train-moon-cloud-blue.png",
    "image_category": "lifestyle"
  },
  "section_3": {
    "section_type": "story",
    "section_name": "Parent Story",
    "component_id": "EMO-5",
    "component_name": "Realistic Timeline",
    "component_source": "A*",
    "image_file": "toddler-rearview-cat-mustard.png",
    "image_category": "lifestyle"
  },
  "section_4": {
    "section_type": "cta",
    "section_name": "CTA",
    "component_id": "FLOW-7",
    "component_name": "Winback Closer",
    "component_source": "A*",
    "image_file": "toddler-outdoors-grass-disposable-diaper.png",
    "image_category": "lifestyle"
  },
  "total_images": 5
}